flask_context_manager/__init__.py
flask_context_manager/flask_context_manager.py
flask_context_manager/relative_path.py
flask_context_manager/src/__init__.py
flask_context_manager/src/main/__init__.py
flask_context_manager/src/main/core/__init__.py
flask_context_manager/src/main/core/context_manager.py
flask_context_manager/src/main/core/routes.py
flask_context_manager/src/main/model/__init__.py
flask_context_manager/src/main/model/bean_wrapper.py
flask_context_manager/src/main/model/beans/__init__.py
flask_context_manager/src/main/model/beans/base_bean.py
flask_context_manager/src/main/model/beans/bean.py
flask_context_manager/src/main/model/beans/component.py
flask_context_manager/src/main/model/beans/configuration.py
flask_context_manager/src/main/model/beans/controller.py
flask_context_manager/src/main/model/beans/repository.py
flask_context_manager/src/main/model/beans/service.py
flask_context_manager/src/main/resources/__init__.py
flask_context_manager/src/main/resources/settings.json
flask_context_manager/src/test/__init__.py
flask_context_manager/src/test/test_app.py
flask_context_manager/src/test/configuration/__init__.py
flask_context_manager/src/test/configuration/a_test_configuration.py
flask_context_manager/src/test/configuration/test_configuration.py
flask_context_manager/src/test/controller/__init__.py
flask_context_manager/src/test/controller/home_controller.py
flask_context_manager/src/test/controller/test_controller.py
flask_context_manager/src/test/service/__init__.py
flask_context_manager/src/test/service/test_service.py
flask_context_manager/src/util/__init__.py
flask_context_manager/src/util/collection_util.py
flask_context_manager-2.0.0.dist-info/LICENSE
flask_context_manager-2.0.0.dist-info/METADATA
flask_context_manager-2.0.0.dist-info/WHEEL
flask_context_manager-2.0.0.dist-info/entry_points.txt
flask_context_manager-2.0.0.dist-info/top_level.txt
flask_context_manager-2.0.0.dist-info/RECORD
