Metadata-Version: 2.1
Name: flask-context-manager
Version: 2.0.0
Summary: A lightweight dependency injection and route management system for Flask, inspired by Spring Boot.
Home-page: https://github.com/rxonhe/flask-context-manager
Author: Rafael Choinhet
Author-email: choinhet@gmail.com
License: MIT
Classifier: Programming Language :: Python :: 3
Classifier: License :: OSI Approved :: MIT License
Classifier: Operating System :: OS Independent
Requires-Python: >=3.10
License-File: LICENSE
Requires-Dist: flask >=3.0.0
Requires-Dist: networkx >=3.3
Requires-Dist: waitress >=3.0.0
